amd_quark-0.10.dist-info/licenses/LICENSE
quark/__init__.py
quark/version.py
quark/contrib/__init__.py
quark/experimental/__init__.py
quark/experimental/cli/__init__.py
quark/experimental/cli/base_cli.py
quark/experimental/cli/main.py
quark/experimental/cli/torch_llm_ptq.py
quark/experimental/cli/quark_onnx/__init__.py
quark/experimental/cli/quark_onnx/export_oga.py
quark/experimental/cli/quark_onnx/export_onnx.py
quark/experimental/cli/quark_onnx/helper_utils.py
quark/experimental/cli/quark_onnx/onnx_prepare_data.py
quark/experimental/cli/quark_onnx/onnx_ptq.py
quark/experimental/cli/quark_onnx/onnx_ptq_autosearch.py
quark/experimental/cli/quark_onnx/onnx_validate.py
quark/experimental/cli/torch_llm/__init__.py
quark/experimental/cli/torch_llm/llm_eval/__init__.py
quark/experimental/cli/torch_llm/llm_eval/custom_lm_eval_harness.py
quark/experimental/cli/torch_llm/llm_eval/evaluation.py
quark/experimental/cli/torch_llm/llm_eval/llm_eval.py
quark/experimental/cli/torch_llm/llm_eval/utilities.py
quark/experimental/cli/torch_llm/llm_eval/example_files/__init__.py
quark/experimental/cli/torch_llm/llm_eval/internal_scripts/__init__.py
quark/experimental/cli/torch_llm/llm_ptq/__init__.py
quark/experimental/cli/torch_llm/llm_ptq/awq_auto_config_helper.py
quark/experimental/cli/torch_llm/llm_ptq/awq_auto_config_helper_v2.py
quark/experimental/cli/torch_llm/llm_ptq/configuration_preparation.py
quark/experimental/cli/torch_llm/llm_ptq/customized_configuration.py
quark/experimental/cli/torch_llm/llm_ptq/internal_scripts/__init__.py
quark/experimental/cli/torch_llm/llm_ptq/internal_scripts/mlperf_data_preparation.py
quark/experimental/cli/torch_llm/llm_ptq/internal_scripts/run_regression_testing_export.py
quark/experimental/cli/torch_llm/llm_utils/__init__.py
quark/experimental/cli/torch_llm/llm_utils/data_preparation.py
quark/experimental/cli/torch_llm/llm_utils/model_preparation.py
quark/experimental/cli/torch_llm/module_replacement/__init__.py
quark/experimental/cli/torch_llm/module_replacement/dbrx_expert.py
amd_quark-0.10.dist-info/METADATA
amd_quark-0.10.dist-info/WHEEL
amd_quark-0.10.dist-info/entry_points.txt
amd_quark-0.10.dist-info/top_level.txt
amd_quark-0.10.dist-info/RECORD
