Metadata-Version: 2.4
Name: amd-quark
Version: 0.10
Summary: AMD Quark is a comprehensive cross-platform toolkit designed to simplify and enhance the quantization of deep learning models. Supporting both PyTorch and ONNX models, AMD Quark empowers developers to optimize their models for deployment on a wide range of hardware backends, achieving significant performance gains without compromising accuracy.
Author: AMD
Author-email: help@amd.com
Maintainer-email: AMD Quark Maintainers <quark.maintainers@amd.com>
License: MIT License
Project-URL: documentation, https://quark.docs.amd.com
Project-URL: homepage, https://github.com/amd/quark
Project-URL: issues, https://github.com/amd/quark/issues
Project-URL: repository, https://github.com/amd/quark.git
Keywords: quantization,pytorch,onnx
Classifier: Development Status :: 5 - Production/Stable
Classifier: Intended Audience :: Developers
Classifier: Intended Audience :: Education
Classifier: Intended Audience :: Science/Research
Classifier: Operating System :: OS Independent
Classifier: Programming Language :: Python :: 3.10
Classifier: Programming Language :: Python :: 3.11
Classifier: Programming Language :: Python :: 3.12
Classifier: Topic :: Scientific/Engineering :: Artificial Intelligence
Requires-Python: >=3.9.0,<3.13
License-File: LICENSE
Requires-Dist: evaluate
Requires-Dist: joblib
Requires-Dist: ninja
Requires-Dist: numpy<=2.1.3
Requires-Dist: onnx<=1.19.0,>=1.16.0
Requires-Dist: onnxruntime<=1.22.1,>=1.20.1
Requires-Dist: onnxruntime_extensions>=0.4.2
Requires-Dist: onnxruntime_genai
Requires-Dist: onnxsim==0.4.36
Requires-Dist: pandas
Requires-Dist: protobuf
Requires-Dist: rich
Requires-Dist: scipy
Requires-Dist: sentencepiece
Requires-Dist: tqdm
Requires-Dist: zstandard
Provides-Extra: lint
Requires-Dist: pyyaml; extra == "lint"
Requires-Dist: ruff; extra == "lint"
Requires-Dist: mypy; extra == "lint"
Requires-Dist: opencv-python; extra == "lint"
Requires-Dist: pre-commit; extra == "lint"
Dynamic: author-email
Dynamic: license-file
Dynamic: requires-python
